neon_tts_plugin_coqui_remote/__init__.py
neon_tts_plugin_coqui_remote/configs.py
neon_tts_plugin_coqui_remote-0.1.0.dist-info/LICENSE.md
neon_tts_plugin_coqui_remote-0.1.0.dist-info/METADATA
neon_tts_plugin_coqui_remote-0.1.0.dist-info/WHEEL
neon_tts_plugin_coqui_remote-0.1.0.dist-info/entry_points.txt
neon_tts_plugin_coqui_remote-0.1.0.dist-info/top_level.txt
neon_tts_plugin_coqui_remote-0.1.0.dist-info/zip-safe
neon_tts_plugin_coqui_remote-0.1.0.dist-info/RECORD
