Metadata-Version: 2.1
Name: neon-tts-plugin-coqui-remote
Version: 0.1.0
Summary: A Coqui AI Remote TTS plugin for Neon
Home-page: https://github.com/NeonGeckoCom/neon-tts-plugin-coqui-remote
Author: Neongecko
Author-email: developers@neon.ai
License: BSD-3.0
Keywords: mycroft plugin tts
Classifier: Intended Audience :: Developers
Classifier: Topic :: Text Processing :: Linguistic
Classifier: Programming Language :: Python :: 3.6
License-File: LICENSE.md
Requires-Dist: ovos-plugin-manager>=0.0.23,~=0.0
Requires-Dist: requests<3.0.0
Requires-Dist: urllib3<3.0.0
